KD_Simulator/__init__.py
KD_Simulator/main.py
kd_simulator-0.2.0.dist-info/METADATA
kd_simulator-0.2.0.dist-info/WHEEL
kd_simulator-0.2.0.dist-info/top_level.txt
kd_simulator-0.2.0.dist-info/RECORD
