Metadata-Version: 2.1
Name: kd-simulator
Version: 0.2.0
Requires-Dist: numpy
Requires-Dist: matplotlib
